{
  "topicId": 232,
  "summaryTitle": "雅思",
  "title": "View & Famous Person",
  "content": {
    "panelTitle": "Question list",
    "panelItemsList": [
      {
        "singleItemContent": [
          "What scenery can you see from the window of your home/dormitory?",
          "Do you like to watch the scenery from your window?",
          "Do you want to live in a house with beautiful windows views?",
          "How do you feel when you cant see any beautiful view from your window?"
        ],
        "singleItemTitle": "PART1"
      },
      {
        "singleItemContent": [
          "Describe a famous person you are interested in",
          "You should say:",
          "Who he/she is",
          "How you knew about him/her",
          "What he/she was like before he/she became famous",
          "And explain why you are interested in him/her"
        ],
        "singleItemTitle": "PART2"
      },
      {
        "singleItemContent": [
          "What kinds of famous people are there in your country?",
          "What are the differences between famous people today and those in the past?",
          "Do you think famous people are necessarily good in their fields?",
          "Do you think media are putting too much attention on famous people?"
        ],
        "singleItemTitle": "PART3"
      }
    ]
  }
}